PyFileIO/FileIO.py
PyFileIO/FileSearch.py
PyFileIO/LoadDict.py
PyFileIO/LoadObject.py
PyFileIO/ReadASCIIData.py
PyFileIO/ReadASCIIFile.py
PyFileIO/RenamedUnpickler.py
PyFileIO/SaveDict.py
PyFileIO/SaveObject.py
PyFileIO/WriteASCIIData.py
PyFileIO/WriteASCIIFile.py
PyFileIO/__init__.py
PyFileIO-0.0.5.dist-info/LICENSE
PyFileIO-0.0.5.dist-info/METADATA
PyFileIO-0.0.5.dist-info/WHEEL
PyFileIO-0.0.5.dist-info/top_level.txt
PyFileIO-0.0.5.dist-info/RECORD
